MANIFEST.in
runtests.py
setup.py
docs/Makefile
docs/amqp.rst
docs/asyncmodel.rst
docs/codegen.rst
docs/conf.py
docs/connection.rst
docs/consuming.rst
docs/direct.svg
docs/fanout.svg
docs/glossary.rst
docs/index.rst
docs/mapreduce.svg
docs/overview.svg
docs/publishing.rst
docs/pubsub.svg
docs/queues_and_exchanges.rst
docs/routing.svg
docs/rpc.svg
docs/topologies.rst
docs/transactions.rst
docs/workers.svg
example/consumer.py
example/publisher.py
nucleon/__init__.py
nucleon.amqp.egg-info/PKG-INFO
nucleon.amqp.egg-info/SOURCES.txt
nucleon.amqp.egg-info/dependency_links.txt
nucleon.amqp.egg-info/namespace_packages.txt
nucleon.amqp.egg-info/requires.txt
nucleon.amqp.egg-info/top_level.txt
nucleon/amqp/__init__.py
nucleon/amqp/buffers.py
nucleon/amqp/channels.py
nucleon/amqp/connection.py
nucleon/amqp/encoding.py
nucleon/amqp/exceptions.py
nucleon/amqp/message.py
nucleon/amqp/spec.py
nucleon/amqp/spec_exceptions.py
nucleon/amqp/table.py
nucleon/amqp/urls.py
tests/base.py
tests/nucleon_tests.py
tests/test_basic.py
tests/test_bug3.py
tests/test_cancel.py
tests/test_channels.py
tests/test_connection.py
tests/test_consume.py
tests/test_exchange.py
tests/test_limits.py
tests/test_messages.py
tests/test_queue.py
tests/tests.py
tests/unittest_backport.py
tests/utils.py