Metadata-Version: 1.1
Name: nucleon.amqp
Version: 0.2.1
Summary: A gevent-based AMQP library with fast, synchronous API
Home-page: https://bitbucket.org/lordmauve/nucleon.amqp
Author: Daniel Pope
Author-email: ext-dan.pope@vertu.com
License: UNKNOWN
Platform: UNKNOWN
Classifier: Development Status :: 4 - Beta
Classifier: Intended Audience :: Developers
Classifier: Operating System :: POSIX
Classifier: Programming Language :: Python
Classifier: License :: OSI Approved :: GNU Lesser General Public License v3 (LGPLv3)
Classifier: Topic :: Software Development :: Libraries :: Python Modules
